gqq521_hello/__init__.py
gqq521_hello-0.1.dist-info/LICENSE.txt
gqq521_hello-0.1.dist-info/METADATA
gqq521_hello-0.1.dist-info/WHEEL
gqq521_hello-0.1.dist-info/top_level.txt
gqq521_hello-0.1.dist-info/RECORD
