Metadata-Version: 2.1
Name: gqq521_hello
Version: 0.1
Summary: A simple hello world package created by GQQ
Home-page: UNKNOWN
Author: GQQ
Author-email: ganqiu@ucdavis.edu
License: MIT
Keywords: sample setuptools development
Platform: UNKNOWN
Classifier: Development Status :: 3 - Alpha
Classifier: License :: OSI Approved :: MIT License
Classifier: Programming Language :: Python :: 3.6
Classifier: Programming Language :: Python :: 3.7
Classifier: Programming Language :: Python :: 3.8
Classifier: Programming Language :: Python :: 3.9
License-File: LICENSE.txt
